agileplanner/__init__.py
agileplanner/src/__init__.py
agileplanner/src/capacitytocsv.py
agileplanner/src/epic.py
agileplanner/src/feature.py
agileplanner/src/holiday.py
agileplanner/src/person.py
agileplanner/src/scheduler.py
agileplanner/src/team.py
agileplanner/src/teamcapacity.py
agileplanner/src/timeperiod.py
agileplanner/tests/__init__.py
agileplanner/tests/test_scheduler.py
agileplanner/tests/test_teamcapacity.py
agileplanner-0.0.3.dist-info/LICENSE
agileplanner-0.0.3.dist-info/METADATA
agileplanner-0.0.3.dist-info/WHEEL
agileplanner-0.0.3.dist-info/top_level.txt
agileplanner-0.0.3.dist-info/RECORD
