Metadata-Version: 2.1
Name: agileplanner
Version: 0.0.3
Summary: Agile planning tools for capacity calculation and basic scheduling of epics.
Home-page: https://github.com/jasondchambers/agileplanner
Author: Jason Chambers
Author-email: jason.d.chambers@gmail.com
License: MIT
Classifier: License :: OSI Approved :: MIT License
Classifier: Programming Language :: Python :: 3.10
Classifier: Operating System :: OS Independent
Classifier: Intended Audience :: Developers
Classifier: Topic :: Office/Business :: Scheduling
Requires-Python: >=3.10
License-File: LICENSE
Requires-Dist: pandas >=2.1.1
Requires-Dist: pyYAML >=6.0.1
Provides-Extra: dev
Requires-Dist: twine >=4.0.2 ; extra == 'dev'
